ukpostalcode.py
ukpostalcode-1.2.dist-info/LICENSE
ukpostalcode-1.2.dist-info/METADATA
ukpostalcode-1.2.dist-info/WHEEL
ukpostalcode-1.2.dist-info/top_level.txt
ukpostalcode-1.2.dist-info/RECORD
