Metadata-Version: 2.1
Name: ukpostalcode
Version: 1.2
Summary: UK Post Code Format and Validation
Home-page: https://git.jquiterio.eu/jquiterio/ukpostalcode
Author: Jorge Quiterio
Author-email: UNKNOWN
License: UNKNOWN
Platform: UNKNOWN
Classifier: Programming Language :: Python :: 3
Classifier: License :: OSI Approved :: MIT License
Classifier: Operating System :: OS Independent
